depender/__init__.py
depender/cli.py
depender/graph/__init__.py
depender/graph/graph.py
depender/graph/layout.py
depender/graph/node.py
depender/parsers/__init__.py
depender/parsers/code.py
depender/parsers/structure.py
depender/render/__init__.py
depender/render/dependency.py
depender/render/render.py
depender/render/structure.py
depender/templates/template.html
depender/utilities/__init__.py
depender/utilities/parsing.py
depender-0.1.2.dist-info/DESCRIPTION.rst
depender-0.1.2.dist-info/METADATA
depender-0.1.2.dist-info/RECORD
depender-0.1.2.dist-info/WHEEL
depender-0.1.2.dist-info/entry_points.txt
depender-0.1.2.dist-info/metadata.json
depender-0.1.2.dist-info/top_level.txt
