Metadata-Version: 2.0
Name: depender
Version: 0.1.2
Summary: A package that finds the external and internal dependencies in your Python projectand draws a directed graph and/or matrix to represent them
Home-page: https://github.com/AnesBenmerzoug/depender
Author: Anes Benmerzoug
Author-email: anes.benmerzoug@gmail.com
License: Apache License 2.0
Platform: UNKNOWN
Classifier: Programming Language :: Python :: 3.5
Classifier: Programming Language :: Python :: 3.6
Classifier: Programming Language :: Python :: 3.7
Classifier: Intended Audience :: Developers
Classifier: License :: OSI Approved :: Apache Software License
Requires-Dist: click (<7.0,>=4.0)
Requires-Dist: click-spinner (>=0.1.0)
Requires-Dist: matplotlib (>=3.0.0)
Requires-Dist: Jinja2 (>=2.9)
Requires-Dist: networkx[scipy] (>=2.3)
Requires-Dist: numpy (>=1.15.4)
